README.md
setup.py
apcs/__init__.py
apcs/addict.py
apcs/config.py
apcs.egg-info/PKG-INFO
apcs.egg-info/SOURCES.txt
apcs.egg-info/dependency_links.txt
apcs.egg-info/requires.txt
apcs.egg-info/top_level.txt
test/test1.py
test/test2.py