Metadata-Version: 1.0
Name: apcs
Version: 0.0.6
Summary: Configuration Toolkit
Home-page: https://github.com/wangjie-ruc/apcs
Author: jie.wang
Author-email: jie.wang@ruc.edu.cn
License: MIT
Platform: UNKNOWN
